{
  "resourceType": "Bundle",
  "type": "transaction",
  "entry": [ {
    "fullUrl": "urn:uuid:8f2fa69d-5631-8623-dcf8-dabc5af99cf4",
    "resource": {
      "resourceType": "Patient",
      "id": "8f2fa69d-5631-8623-dcf8-dabc5af99cf4",
      "text": {
        "status": "generated",
        "div": "<div xmlns=\"http://www.w3.org/1999/xhtml\">Generated by <a href=\"https://github.com/synthetichealth/synthea\">Synthea</a>.Version identifier: 77398b2\n .   Person seed: 4361642060525275343  Population seed: 1720565243727</div>"
      },
      "extension": [ {
        "url": "http://hl7.org/fhir/StructureDefinition/patient-mothersMaidenName",
        "valueString": "Shawna986 Dicki44"
      }, {
        "url": "http://hl7.org/fhir/StructureDefinition/patient-birthPlace",
        "valueAddress": {
          "city": "Reading",
          "state": "Massachusetts",
          "country": "US"
        }
      }, {
        "url": "http://synthetichealth.github.io/synthea/disability-adjusted-life-years",
        "valueDecimal": 6.387236432051324
      }, {
        "url": "http://synthetichealth.github.io/synthea/quality-adjusted-life-years",
        "valueDecimal": 42.612763567948676
      } ],
      "identifier": [ {
        "system": "https://github.com/synthetichealth/synthea",
        "value": "8f2fa69d-5631-8623-dcf8-dabc5af99cf4"
      }, {
        "type": {
          "coding": [ {
            "system": "http://terminology.hl7.org/CodeSystem/v2-0203",
            "code": "MR",
            "display": "Medical Record Number"
          } ],
          "text": "Medical Record Number"
        },
        "system": "http://hospital.smarthealthit.org",
        "value": "8f2fa69d-5631-8623-dcf8-dabc5af99cf4"
      }, {
        "type": {
          "coding": [ {
            "system": "http://terminology.hl7.org/CodeSystem/v2-0203",
            "code": "SS",
            "display": "Social Security Number"
          } ],
          "text": "Social Security Number"
        },
        "system": "http://hl7.org/fhir/sid/us-ssn",
        "value": "999-49-4523"
      }, {
        "type": {
          "coding": [ {
            "system": "http://terminology.hl7.org/CodeSystem/v2-0203",
            "code": "DL",
            "display": "Driver's license number"
          } ],
          "text": "Driver's license number"
        },
        "system": "urn:oid:2.16.840.1.113883.4.3.25",
        "value": "S99970604"
      }, {
        "type": {
          "coding": [ {
            "system": "http://terminology.hl7.org/CodeSystem/v2-0203",
            "code": "PPN",
            "display": "Passport Number"
          } ],
          "text": "Passport Number"
        },
        "system": "http://standardhealthrecord.org/fhir/StructureDefinition/passportNumber",
        "value": "X87191865X"
      } ],
      "name": [ {
        "use": "official",
        "family": "Russel238",
        "given": [ "Seymour882", "Lou594" ],
        "prefix": [ "Mr." ]
      } ],
      "telecom": [ {
        "system": "phone",
        "value": "555-773-8060",
        "use": "home"
      } ],
      "gender": "male",
      "birthDate": "1974-09-30",
      "address": [ {
        "extension": [ {
          "url": "http://hl7.org/fhir/StructureDefinition/geolocation",
          "extension": [ {
            "url": "latitude",
            "valueDecimal": 42.681601453447
          }, {
            "url": "longitude",
            "valueDecimal": -71.27875341290118
          } ]
        } ],
        "line": [ "829 Feeney Rue Suite 29" ],
        "city": "Dracut",
        "state": "Massachusetts",
        "postalCode": "00000",
        "country": "US"
      } ],
      "maritalStatus": {
        "coding": [ {
          "system": "http://terminology.hl7.org/CodeSystem/v3-MaritalStatus",
          "code": "M",
          "display": "Married"
        } ],
        "text": "Married"
      },
      "multipleBirthBoolean": false,
      "communication": [ {
        "language": {
          "coding": [ {
            "system": "urn:ietf:bcp:47",
            "code": "en-US",
            "display": "English (United States)"
          } ],
          "text": "English (United States)"
        }
      } ]
    },
    "request": {
      "method": "POST",
      "url": "Patient"
    }
  }, {
    "fullUrl": "urn:uuid:2172ad21-a938-cadc-202e-1e728174c2ca",
    "resource": {
      "resourceType": "Encounter",
      "id": "2172ad21-a938-cadc-202e-1e728174c2ca",
      "status": "finished",
      "class": {
        "system": "http://terminology.hl7.org/CodeSystem/v3-ActCode",
        "code": "AMB"
      },
      "type": [ {
        "coding": [ {
          "system": "http://snomed.info/sct",
          "code": "162673000",
          "display": "General examination of patient (procedure)"
        } ],
        "text": "General examination of patient (procedure)"
      } ],
      "subject": {
        "reference": "urn:uuid:8f2fa69d-5631-8623-dcf8-dabc5af99cf4",
        "display": "Mr. Seymour882 Lou594 Russel238"
      },
      "participant": [ {
        "type": [ {
          "coding": [ {
            "system": "http://terminology.hl7.org/CodeSystem/v3-ParticipationType",
            "code": "PPRF",
            "display": "primary performer"
          } ],
          "text": "primary performer"
        } ],
        "period": {
          "start": "1992-11-23T05:37:16-08:00",
          "end": "1992-11-23T06:23:24-08:00"
        },
        "individual": {
          "reference": "Practitioner?identifier=http://hl7.org/fhir/sid/us-npi|9999963595",
          "display": "Dr. Jordon466 Bruen238"
        }
      } ],
      "period": {
        "start": "1992-11-23T05:37:16-08:00",
        "end": "1992-11-23T06:23:24-08:00"
      },
      "serviceProvider": {
        "reference": "Organization?identifier=https://github.com/synthetichealth/synthea|19f958ef-57cf-33c1-b068-14b32a980813",
        "display": "DRACUT FAMILY HEALTHCARE"
      }
    },
    "request": {
      "method": "POST",
      "url": "Encounter"
    }
  }, {
    "fullUrl": "urn:uuid:3eb6b590-1b34-545d-c01f-f45391774084",
    "resource": {
      "resourceType": "Encounter",
      "id": "3eb6b590-1b34-545d-c01f-f45391774084",
      "status": "finished",
      "class": {
        "system": "http://terminology.hl7.org/CodeSystem/v3-ActCode",
        "code": "AMB"
      },
      "type": [ {
        "coding": [ {
          "system": "http://snomed.info/sct",
          "code": "185345009",
          "display": "Encounter for symptom"
        } ],
        "text": "Encounter for symptom"
      } ],
      "subject": {
        "reference": "urn:uuid:8f2fa69d-5631-8623-dcf8-dabc5af99cf4",
        "display": "Mr. Seymour882 Lou594 Russel238"
      },
      "participant": [ {
        "type": [ {
          "coding": [ {
            "system": "http://terminology.hl7.org/CodeSystem/v3-ParticipationType",
            "code": "PPRF",
            "display": "primary performer"
          } ],
          "text": "primary performer"
        } ],
        "period": {
          "start": "2005-03-29T10:37:16-08:00",
          "end": "2005-03-29T10:52:16-08:00"
        },
        "individual": {
          "reference": "Practitioner?identifier=http://hl7.org/fhir/sid/us-npi|9999994491",
          "display": "Dr. Alysha630 Koch169"
        }
      } ],
      "period": {
        "start": "2005-03-29T10:37:16-08:00",
        "end": "2005-03-29T10:52:16-08:00"
      },
      "reasonCode": [ {
        "coding": [ {
          "system": "http://snomed.info/sct",
          "code": "36971009",
          "display": "Sinusitis (disorder)"
        } ]
      } ],
      "serviceProvider": {
        "reference": "Organization?identifier=https://github.com/synthetichealth/synthea|2836d9ac-c6a6-39d1-8f13-fdf0fc8928f4",
        "display": "TEWKSBURY HOSPITAL"
      }
    },
    "request": {
      "method": "POST",
      "url": "Encounter"
    }
  }, {
    "fullUrl": "urn:uuid:ad4127b8-3d8e-d1ee-9399-bc2193f48ee5",
    "resource": {
      "resourceType": "Encounter",
      "id": "ad4127b8-3d8e-d1ee-9399-bc2193f48ee5",
      "status": "finished",
      "class": {
        "system": "http://terminology.hl7.org/CodeSystem/v3-ActCode",
        "code": "AMB"
      },
      "type": [ {
        "coding": [ {
          "system": "http://snomed.info/sct",
          "code": "162673000",
          "display": "General examination of patient (procedure)"
        } ],
        "text": "General examination of patient (procedure)"
      } ],
      "subject": {
        "reference": "urn:uuid:8f2fa69d-5631-8623-dcf8-dabc5af99cf4",
        "display": "Mr. Seymour882 Lou594 Russel238"
      },
      "participant": [ {
        "type": [ {
          "coding": [ {
            "system": "http://terminology.hl7.org/CodeSystem/v3-ParticipationType",
            "code": "PPRF",
            "display": "primary performer"
          } ],
          "text": "primary performer"
        } ],
        "period": {
          "start": "2008-12-15T05:37:16-08:00",
          "end": "2008-12-15T06:27:33-08:00"
        },
        "individual": {
          "reference": "Practitioner?identifier=http://hl7.org/fhir/sid/us-npi|9999963595",
          "display": "Dr. Jordon466 Bruen238"
        }
      } ],
      "period": {
        "start": "2008-12-15T05:37:16-08:00",
        "end": "2008-12-15T06:27:33-08:00"
      },
      "serviceProvider": {
        "reference": "Organization?identifier=https://github.com/synthetichealth/synthea|19f958ef-57cf-33c1-b068-14b32a980813",
        "display": "DRACUT FAMILY HEALTHCARE"
      }
    },
    "request": {
      "method": "POST",
      "url": "Encounter"
    }
  }, {
    "fullUrl": "urn:uuid:de4a921b-4a8f-5669-4b0f-8375e08cf1b7",
    "resource": {
      "resourceType": "Encounter",
      "id": "de4a921b-4a8f-5669-4b0f-8375e08cf1b7",
      "status": "finished",
      "class": {
        "system": "http://terminology.hl7.org/CodeSystem/v3-ActCode",
        "code": "AMB"
      },
      "type": [ {
        "coding": [ {
          "system": "http://snomed.info/sct",
          "code": "162673000",
          "display": "General examination of patient (procedure)"
        } ],
        "text": "General examination of patient (procedure)"
      } ],
      "subject": {
        "reference": "urn:uuid:8f2fa69d-5631-8623-dcf8-dabc5af99cf4",
        "display": "Mr. Seymour882 Lou594 Russel238"
      },
      "participant": [ {
        "type": [ {
          "coding": [ {
            "system": "http://terminology.hl7.org/CodeSystem/v3-ParticipationType",
            "code": "PPRF",
            "display": "primary performer"
          } ],
          "text": "primary performer"
        } ],
        "period": {
          "start": "2011-12-19T05:37:16-08:00",
          "end": "2011-12-19T06:36:54-08:00"
        },
        "individual": {
          "reference": "Practitioner?identifier=http://hl7.org/fhir/sid/us-npi|9999963595",
          "display": "Dr. Jordon466 Bruen238"
        }
      } ],
      "period": {
        "start": "2011-12-19T05:37:16-08:00",
        "end": "2011-12-19T06:36:54-08:00"
      },
      "serviceProvider": {
        "reference": "Organization?identifier=https://github.com/synthetichealth/synthea|19f958ef-57cf-33c1-b068-14b32a980813",
        "display": "DRACUT FAMILY HEALTHCARE"
      }
    },
    "request": {
      "method": "POST",
      "url": "Encounter"
    }
  }, {
    "fullUrl": "urn:uuid:1812d8a9-0a02-327d-6889-603fcbb514bb",
    "resource": {
      "resourceType": "Encounter",
      "id": "1812d8a9-0a02-327d-6889-603fcbb514bb",
      "status": "finished",
      "class": {
        "system": "http://terminology.hl7.org/CodeSystem/v3-ActCode",
        "code": "AMB"
      },
      "type": [ {
        "coding": [ {
          "system": "http://snomed.info/sct",
          "code": "702927004",
          "display": "Urgent care clinic (environment)"
        } ],
        "text": "Urgent care clinic (environment)"
      } ],
      "subject": {
        "reference": "urn:uuid:8f2fa69d-5631-8623-dcf8-dabc5af99cf4",
        "display": "Mr. Seymour882 Lou594 Russel238"
      },
      "participant": [ {
        "type": [ {
          "coding": [ {
            "system": "http://terminology.hl7.org/CodeSystem/v3-ParticipationType",
            "code": "PPRF",
            "display": "primary performer"
          } ],
          "text": "primary performer"
        } ],
        "period": {
          "start": "2012-11-05T05:37:16-08:00",
          "end": "2012-11-05T06:25:44-08:00"
        },
        "individual": {
          "reference": "Practitioner?identifier=http://hl7.org/fhir/sid/us-npi|9999938498",
          "display": "Dr. Rema399 McDermott739"
        }
      } ],
      "period": {
        "start": "2012-11-05T05:37:16-08:00",
        "end": "2012-11-05T06:25:44-08:00"
      },
      "serviceProvider": {
        "reference": "Organization?identifier=https://github.com/synthetichealth/synthea|c05d73d0-b348-32ce-9fe5-13a720950f37",
        "display": "URGENT HELP CHELMSFORD PC"
      }
    },
    "request": {
      "method": "POST",
      "url": "Encounter"
    }
  }, {
    "fullUrl": "urn:uuid:62554a85-96d2-58f6-4502-229e0ed62fb0",
    "resource": {
      "resourceType": "Encounter",
      "id": "62554a85-96d2-58f6-4502-229e0ed62fb0",
      "status": "finished",
      "class": {
        "system": "http://terminology.hl7.org/CodeSystem/v3-ActCode",
        "code": "AMB"
      },
      "type": [ {
        "coding": [ {
          "system": "http://snomed.info/sct",
          "code": "185345009",
          "display": "Encounter for symptom"
        } ],
        "text": "Encounter for symptom"
      } ],
      "subject": {
        "reference": "urn:uuid:8f2fa69d-5631-8623-dcf8-dabc5af99cf4",
        "display": "Mr. Seymour882 Lou594 Russel238"
      },
      "participant": [ {
        "type": [ {
          "coding": [ {
            "system": "http://terminology.hl7.org/CodeSystem/v3-ParticipationType",
            "code": "PPRF",
            "display": "primary performer"
          } ],
          "text": "primary performer"
        } ],
        "period": {
          "start": "2014-03-23T00:37:16-07:00",
          "end": "2014-03-23T00:52:16-07:00"
        },
        "individual": {
          "reference": "Practitioner?identifier=http://hl7.org/fhir/sid/us-npi|9999994491",
          "display": "Dr. Alysha630 Koch169"
        }
      } ],
      "period": {
        "start": "2014-03-23T00:37:16-07:00",
        "end": "2014-03-23T00:52:16-07:00"
      },
      "reasonCode": [ {
        "coding": [ {
          "system": "http://snomed.info/sct",
          "code": "10509002",
          "display": "Acute bronchitis (disorder)"
        } ]
      } ],
      "serviceProvider": {
        "reference": "Organization?identifier=https://github.com/synthetichealth/synthea|2836d9ac-c6a6-39d1-8f13-fdf0fc8928f4",
        "display": "TEWKSBURY HOSPITAL"
      }
    },
    "request": {
      "method": "POST",
      "url": "Encounter"
    }
  }, {
    "fullUrl": "urn:uuid:bf2882bb-8118-8eb2-b34b-d74b817cd1a8",
    "resource": {
      "resourceType": "Encounter",
      "id": "bf2882bb-8118-8eb2-b34b-d74b817cd1a8",
      "status": "finished",
      "class": {
        "system": "http://terminology.hl7.org/CodeSystem/v3-ActCode",
        "code": "AMB"
      },
      "type": [ {
        "coding": [ {
          "system": "http://snomed.info/sct",
          "code": "185349003",
          "display": "Encounter for check up (procedure)"
        } ],
        "text": "Encounter for check up (procedure)"
      } ],
      "subject": {
        "reference": "urn:uuid:8f2fa69d-5631-8623-dcf8-dabc5af99cf4",
        "display": "Mr. Seymour882 Lou594 Russel238"
      },
      "participant": [ {
        "type": [ {
          "coding": [ {
            "system": "http://terminology.hl7.org/CodeSystem/v3-ParticipationType",
            "code": "PPRF",
            "display": "primary performer"
          } ],
          "text": "primary performer"
        } ],
        "period": {
          "start": "2014-04-07T06:37:16-07:00",
          "end": "2014-04-07T06:52:16-07:00"
        },
        "individual": {
          "reference": "Practitioner?identifier=http://hl7.org/fhir/sid/us-npi|9999994491",
          "display": "Dr. Alysha630 Koch169"
        }
      } ],
      "period": {
        "start": "2014-04-07T06:37:16-07:00",
        "end": "2014-04-07T06:52:16-07:00"
      },
      "serviceProvider": {
        "reference": "Organization?identifier=https://github.com/synthetichealth/synthea|2836d9ac-c6a6-39d1-8f13-fdf0fc8928f4",
        "display": "TEWKSBURY HOSPITAL"
      }
    },
    "request": {
      "method": "POST",
      "url": "Encounter"
    }
  }, {
    "fullUrl": "urn:uuid:42ee0251-340f-6014-2861-09d84ce21150",
    "resource": {
      "resourceType": "Encounter",
      "id": "42ee0251-340f-6014-2861-09d84ce21150",
      "status": "finished",
      "class": {
        "system": "http://terminology.hl7.org/CodeSystem/v3-ActCode",
        "code": "AMB"
      },
      "type": [ {
        "coding": [ {
          "system": "http://snomed.info/sct",
          "code": "185349003",
          "display": "Encounter for check up (procedure)"
        } ],
        "text": "Encounter for check up (procedure)"
      } ],
      "subject": {
        "reference": "urn:uuid:8f2fa69d-5631-8623-dcf8-dabc5af99cf4",
        "display": "Mr. Seymour882 Lou594 Russel238"
      },
      "participant": [ {
        "type": [ {
          "coding": [ {
            "system": "http://terminology.hl7.org/CodeSystem/v3-ParticipationType",
            "code": "PPRF",
            "display": "primary performer"
          } ],
          "text": "primary performer"
        } ],
        "period": {
          "start": "2014-10-27T06:37:16-07:00",
          "end": "2014-10-27T07:21:34-07:00"
        },
        "individual": {
          "reference": "Practitioner?identifier=http://hl7.org/fhir/sid/us-npi|9999994491",
          "display": "Dr. Alysha630 Koch169"
        }
      } ],
      "period": {
        "start": "2014-10-27T06:37:16-07:00",
        "end": "2014-10-27T07:21:34-07:00"
      },
      "serviceProvider": {
        "reference": "Organization?identifier=https://github.com/synthetichealth/synthea|2836d9ac-c6a6-39d1-8f13-fdf0fc8928f4",
        "display": "TEWKSBURY HOSPITAL"
      }
    },
    "request": {
      "method": "POST",
      "url": "Encounter"
    }
  }, {
    "fullUrl": "urn:uuid:0b2fdbce-6e26-0424-ecb5-760b7603a90a",
    "resource": {
      "resourceType": "Encounter",
      "id": "0b2fdbce-6e26-0424-ecb5-760b7603a90a",
      "status": "finished",
      "class": {
        "system": "http://terminology.hl7.org/CodeSystem/v3-ActCode",
        "code": "AMB"
      },
      "type": [ {
        "coding": [ {
          "system": "http://snomed.info/sct",
          "code": "185349003",
          "display": "Encounter for check up (procedure)"
        } ],
        "text": "Encounter for check up (procedure)"
      } ],
      "subject": {
        "reference": "urn:uuid:8f2fa69d-5631-8623-dcf8-dabc5af99cf4",
        "display": "Mr. Seymour882 Lou594 Russel238"
      },
      "participant": [ {
        "type": [ {
          "coding": [ {
            "system": "http://terminology.hl7.org/CodeSystem/v3-ParticipationType",
            "code": "PPRF",
            "display": "primary performer"
          } ],
          "text": "primary performer"
        } ],
        "period": {
          "start": "2014-12-01T05:37:16-08:00",
          "end": "2014-12-01T06:19:07-08:00"
        },
        "individual": {
          "reference": "Practitioner?identifier=http://hl7.org/fhir/sid/us-npi|9999994491",
          "display": "Dr. Alysha630 Koch169"
        }
      } ],
      "period": {
        "start": "2014-12-01T05:37:16-08:00",
        "end": "2014-12-01T06:19:07-08:00"
      },
      "serviceProvider": {
        "reference": "Organization?identifier=https://github.com/synthetichealth/synthea|2836d9ac-c6a6-39d1-8f13-fdf0fc8928f4",
        "display": "TEWKSBURY HOSPITAL"
      }
    },
    "request": {
      "method": "POST",
      "url": "Encounter"
    }
  }, {
    "fullUrl": "urn:uuid:74a6ac7e-1d01-6461-9494-6c70f9ec75bc",
    "resource": {
      "resourceType": "Encounter",
      "id": "74a6ac7e-1d01-6461-9494-6c70f9ec75bc",
      "status": "finished",
      "class": {
        "system": "http://terminology.hl7.org/CodeSystem/v3-ActCode",
        "code": "AMB"
      },
      "type": [ {
        "coding": [ {
          "system": "http://snomed.info/sct",
          "code": "162673000",
          "display": "General examination of patient (procedure)"
        } ],
        "text": "General examination of patient (procedure)"
      } ],
      "subject": {
        "reference": "urn:uuid:8f2fa69d-5631-8623-dcf8-dabc5af99cf4",
        "display": "Mr. Seymour882 Lou594 Russel238"
      },
      "participant": [ {
        "type": [ {
          "coding": [ {
            "system": "http://terminology.hl7.org/CodeSystem/v3-ParticipationType",
            "code": "PPRF",
            "display": "primary performer"
          } ],
          "text": "primary performer"
        } ],
        "period": {
          "start": "2015-01-05T05:37:16-08:00",
          "end": "2015-01-05T06:10:58-08:00"
        },
        "individual": {
          "reference": "Practitioner?identifier=http://hl7.org/fhir/sid/us-npi|9999963595",
          "display": "Dr. Jordon466 Bruen238"
        }
      } ],
      "period": {
        "start": "2015-01-05T05:37:16-08:00",
        "end": "2015-01-05T06:10:58-08:00"
      },
      "serviceProvider": {
        "reference": "Organization?identifier=https://github.com/synthetichealth/synthea|19f958ef-57cf-33c1-b068-14b32a980813",
        "display": "DRACUT FAMILY HEALTHCARE"
      }
    },
    "request": {
      "method": "POST",
      "url": "Encounter"
    }
  }, {
    "fullUrl": "urn:uuid:25843ef0-87ce-b134-2e3f-b22fb9197e76",
    "resource": {
      "resourceType": "Encounter",
      "id": "25843ef0-87ce-b134-2e3f-b22fb9197e76",
      "status": "finished",
      "class": {
        "system": "http://terminology.hl7.org/CodeSystem/v3-ActCode",
        "code": "AMB"
      },
      "type": [ {
        "coding": [ {
          "system": "http://snomed.info/sct",
          "code": "162673000",
          "display": "General examination of patient (procedure)"
        } ],
        "text": "General examination of patient (procedure)"
      } ],
      "subject": {
        "reference": "urn:uuid:8f2fa69d-5631-8623-dcf8-dabc5af99cf4",
        "display": "Mr. Seymour882 Lou594 Russel238"
      },
      "participant": [ {
        "type": [ {
          "coding": [ {
            "system": "http://terminology.hl7.org/CodeSystem/v3-ParticipationType",
            "code": "PPRF",
            "display": "primary performer"
          } ],
          "text": "primary performer"
        } ],
        "period": {
          "start": "2016-01-11T05:37:16-08:00",
          "end": "2016-01-11T06:08:27-08:00"
        },
        "individual": {
          "reference": "Practitioner?identifier=http://hl7.org/fhir/sid/us-npi|9999963595",
          "display": "Dr. Jordon466 Bruen238"
        }
      } ],
      "period": {
        "start": "2016-01-11T05:37:16-08:00",
        "end": "2016-01-11T06:08:27-08:00"
      },
      "serviceProvider": {
        "reference": "Organization?identifier=https://github.com/synthetichealth/synthea|19f958ef-57cf-33c1-b068-14b32a980813",
        "display": "DRACUT FAMILY HEALTHCARE"
      }
    },
    "request": {
      "method": "POST",
      "url": "Encounter"
    }
  }, {
    "fullUrl": "urn:uuid:fc1623c4-b3ca-8611-2d47-c8f567d104ab",
    "resource": {
      "resourceType": "Encounter",
      "id": "fc1623c4-b3ca-8611-2d47-c8f567d104ab",
      "status": "finished",
      "class": {
        "system": "http://terminology.hl7.org/CodeSystem/v3-ActCode",
        "code": "AMB"
      },
      "type": [ {
        "coding": [ {
          "system": "http://snomed.info/sct",
          "code": "185349003",
          "display": "Encounter for check up (procedure)"
        } ],
        "text": "Encounter for check up (procedure)"
      } ],
      "subject": {
        "reference": "urn:uuid:8f2fa69d-5631-8623-dcf8-dabc5af99cf4",
        "display": "Mr. Seymour882 Lou594 Russel238"
      },
      "participant": [ {
        "type": [ {
          "coding": [ {
            "system": "http://terminology.hl7.org/CodeSystem/v3-ParticipationType",
            "code": "PPRF",
            "display": "primary performer"
          } ],
          "text": "primary performer"
        } ],
        "period": {
          "start": "2016-09-19T06:37:16-07:00",
          "end": "2016-09-19T07:16:38-07:00"
        },
        "individual": {
          "reference": "Practitioner?identifier=http://hl7.org/fhir/sid/us-npi|9999994491",
          "display": "Dr. Alysha630 Koch169"
        }
      } ],
      "period": {
        "start": "2016-09-19T06:37:16-07:00",
        "end": "2016-09-19T07:16:38-07:00"
      },
      "serviceProvider": {
        "reference": "Organization?identifier=https://github.com/synthetichealth/synthea|2836d9ac-c6a6-39d1-8f13-fdf0fc8928f4",
        "display": "TEWKSBURY HOSPITAL"
      }
    },
    "request": {
      "method": "POST",
      "url": "Encounter"
    }
  }, {
    "fullUrl": "urn:uuid:5657ade0-b7b6-cbba-385e-5df29a17a841",
    "resource": {
      "resourceType": "Encounter",
      "id": "5657ade0-b7b6-cbba-385e-5df29a17a841",
      "status": "finished",
      "class": {
        "system": "http://terminology.hl7.org/CodeSystem/v3-ActCode",
        "code": "AMB"
      },
      "type": [ {
        "coding": [ {
          "system": "http://snomed.info/sct",
          "code": "162673000",
          "display": "General examination of patient (procedure)"
        } ],
        "text": "General examination of patient (procedure)"
      } ],
      "subject": {
        "reference": "urn:uuid:8f2fa69d-5631-8623-dcf8-dabc5af99cf4",
        "display": "Mr. Seymour882 Lou594 Russel238"
      },
      "participant": [ {
        "type": [ {
          "coding": [ {
            "system": "http://terminology.hl7.org/CodeSystem/v3-ParticipationType",
            "code": "PPRF",
            "display": "primary performer"
          } ],
          "text": "primary performer"
        } ],
        "period": {
          "start": "2017-01-16T05:37:16-08:00",
          "end": "2017-01-16T06:33:22-08:00"
        },
        "individual": {
          "reference": "Practitioner?identifier=http://hl7.org/fhir/sid/us-npi|9999963595",
          "display": "Dr. Jordon466 Bruen238"
        }
      } ],
      "period": {
        "start": "2017-01-16T05:37:16-08:00",
        "end": "2017-01-16T06:33:22-08:00"
      },
      "serviceProvider": {
        "reference": "Organization?identifier=https://github.com/synthetichealth/synthea|19f958ef-57cf-33c1-b068-14b32a980813",
        "display": "DRACUT FAMILY HEALTHCARE"
      }
    },
    "request": {
      "method": "POST",
      "url": "Encounter"
    }
  }, {
    "fullUrl": "urn:uuid:1625c650-d882-738c-6e6f-643917326f7b",
    "resource": {
      "resourceType": "Encounter",
      "id": "1625c650-d882-738c-6e6f-643917326f7b",
      "status": "finished",
      "class": {
        "system": "http://terminology.hl7.org/CodeSystem/v3-ActCode",
        "code": "AMB"
      },
      "type": [ {
        "coding": [ {
          "system": "http://snomed.info/sct",
          "code": "185349003",
          "display": "Encounter for check up (procedure)"
        } ],
        "text": "Encounter for check up (procedure)"
      } ],
      "subject": {
        "reference": "urn:uuid:8f2fa69d-5631-8623-dcf8-dabc5af99cf4",
        "display": "Mr. Seymour882 Lou594 Russel238"
      },
      "participant": [ {
        "type": [ {
          "coding": [ {
            "system": "http://terminology.hl7.org/CodeSystem/v3-ParticipationType",
            "code": "PPRF",
            "display": "primary performer"
          } ],
          "text": "primary performer"
        } ],
        "period": {
          "start": "2017-04-17T06:37:16-07:00",
          "end": "2017-04-17T07:07:21-07:00"
        },
        "individual": {
          "reference": "Practitioner?identifier=http://hl7.org/fhir/sid/us-npi|9999994491",
          "display": "Dr. Alysha630 Koch169"
        }
      } ],
      "period": {
        "start": "2017-04-17T06:37:16-07:00",
        "end": "2017-04-17T07:07:21-07:00"
      },
      "serviceProvider": {
        "reference": "Organization?identifier=https://github.com/synthetichealth/synthea|2836d9ac-c6a6-39d1-8f13-fdf0fc8928f4",
        "display": "TEWKSBURY HOSPITAL"
      }
    },
    "request": {
      "method": "POST",
      "url": "Encounter"
    }
  }, {
    "fullUrl": "urn:uuid:596e7dbd-bd0a-5304-0fb6-0d945c0de4a4",
    "resource": {
      "resourceType": "Encounter",
      "id": "596e7dbd-bd0a-5304-0fb6-0d945c0de4a4",
      "status": "finished",
      "class": {
        "system": "http://terminology.hl7.org/CodeSystem/v3-ActCode",
        "code": "AMB"
      },
      "type": [ {
        "coding": [ {
          "system": "http://snomed.info/sct",
          "code": "162673000",
          "display": "General examination of patient (procedure)"
        } ],
        "text": "General examination of patient (procedure)"
      } ],
      "subject": {
        "reference": "urn:uuid:8f2fa69d-5631-8623-dcf8-dabc5af99cf4",
        "display": "Mr. Seymour882 Lou594 Russel238"
      },
      "participant": [ {
        "type": [ {
          "coding": [ {
            "system": "http://terminology.hl7.org/CodeSystem/v3-ParticipationType",
            "code": "PPRF",
            "display": "primary performer"
          } ],
          "text": "primary performer"
        } ],
        "period": {
          "start": "2018-01-22T05:37:16-08:00",
          "end": "2018-01-22T06:18:32-08:00"
        },
        "individual": {
          "reference": "Practitioner?identifier=http://hl7.org/fhir/sid/us-npi|9999963595",
          "display": "Dr. Jordon466 Bruen238"
        }
      } ],
      "period": {
        "start": "2018-01-22T05:37:16-08:00",
        "end": "2018-01-22T06:18:32-08:00"
      },
      "serviceProvider": {
        "reference": "Organization?identifier=https://github.com/synthetichealth/synthea|19f958ef-57cf-33c1-b068-14b32a980813",
        "display": "DRACUT FAMILY HEALTHCARE"
      }
    },
    "request": {
      "method": "POST",
      "url": "Encounter"
    }
  }, {
    "fullUrl": "urn:uuid:db1afb97-c70e-9d08-69b6-c8fca2dff8df",
    "resource": {
      "resourceType": "Encounter",
      "id": "db1afb97-c70e-9d08-69b6-c8fca2dff8df",
      "status": "finished",
      "class": {
        "system": "http://terminology.hl7.org/CodeSystem/v3-ActCode",
        "code": "AMB"
      },
      "type": [ {
        "coding": [ {
          "system": "http://snomed.info/sct",
          "code": "185349003",
          "display": "Encounter for check up (procedure)"
        } ],
        "text": "Encounter for check up (procedure)"
      } ],
      "subject": {
        "reference": "urn:uuid:8f2fa69d-5631-8623-dcf8-dabc5af99cf4",
        "display": "Mr. Seymour882 Lou594 Russel238"
      },
      "participant": [ {
        "type": [ {
          "coding": [ {
            "system": "http://terminology.hl7.org/CodeSystem/v3-ParticipationType",
            "code": "PPRF",
            "display": "primary performer"
          } ],
          "text": "primary performer"
        } ],
        "period": {
          "start": "2018-04-09T06:37:16-07:00",
          "end": "2018-04-09T07:31:03-07:00"
        },
        "individual": {
          "reference": "Practitioner?identifier=http://hl7.org/fhir/sid/us-npi|9999994491",
          "display": "Dr. Alysha630 Koch169"
        }
      } ],
      "period": {
        "start": "2018-04-09T06:37:16-07:00",
        "end": "2018-04-09T07:31:03-07:00"
      },
      "serviceProvider": {
        "reference": "Organization?identifier=https://github.com/synthetichealth/synthea|2836d9ac-c6a6-39d1-8f13-fdf0fc8928f4",
        "display": "TEWKSBURY HOSPITAL"
      }
    },
    "request": {
      "method": "POST",
      "url": "Encounter"
    }
  }, {
    "fullUrl": "urn:uuid:a3187df4-860c-a854-4001-7ef2efe2f122",
    "resource": {
      "resourceType": "Encounter",
      "id": "a3187df4-860c-a854-4001-7ef2efe2f122",
      "status": "finished",
      "class": {
        "system": "http://terminology.hl7.org/CodeSystem/v3-ActCode",
        "code": "AMB"
      },
      "type": [ {
        "coding": [ {
          "system": "http://snomed.info/sct",
          "code": "185349003",
          "display": "Encounter for check up (procedure)"
        } ],
        "text": "Encounter for check up (procedure)"
      } ],
      "subject": {
        "reference": "urn:uuid:8f2fa69d-5631-8623-dcf8-dabc5af99cf4",
        "display": "Mr. Seymour882 Lou594 Russel238"
      },
      "participant": [ {
        "type": [ {
          "coding": [ {
            "system": "http://terminology.hl7.org/CodeSystem/v3-ParticipationType",
            "code": "PPRF",
            "display": "primary performer"
          } ],
          "text": "primary performer"
        } ],
        "period": {
          "start": "2018-11-05T05:37:16-08:00",
          "end": "2018-11-05T06:17:33-08:00"
        },
        "individual": {
          "reference": "Practitioner?identifier=http://hl7.org/fhir/sid/us-npi|9999994491",
          "display": "Dr. Alysha630 Koch169"
        }
      } ],
      "period": {
        "start": "2018-11-05T05:37:16-08:00",
        "end": "2018-11-05T06:17:33-08:00"
      },
      "serviceProvider": {
        "reference": "Organization?identifier=https://github.com/synthetichealth/synthea|2836d9ac-c6a6-39d1-8f13-fdf0fc8928f4",
        "display": "TEWKSBURY HOSPITAL"
      }
    },
    "request": {
      "method": "POST",
      "url": "Encounter"
    }
  }, {
    "fullUrl": "urn:uuid:49b9e170-826c-926a-d3b7-6d92713daf5c",
    "resource": {
      "resourceType": "Encounter",
      "id": "49b9e170-826c-926a-d3b7-6d92713daf5c",
      "status": "finished",
      "class": {
        "system": "http://terminology.hl7.org/CodeSystem/v3-ActCode",
        "code": "AMB"
      },
      "type": [ {
        "coding": [ {
          "system": "http://snomed.info/sct",
          "code": "162673000",
          "display": "General examination of patient (procedure)"
        } ],
        "text": "General examination of patient (procedure)"
      } ],
      "subject": {
        "reference": "urn:uuid:8f2fa69d-5631-8623-dcf8-dabc5af99cf4",
        "display": "Mr. Seymour882 Lou594 Russel238"
      },
      "participant": [ {
        "type": [ {
          "coding": [ {
            "system": "http://terminology.hl7.org/CodeSystem/v3-ParticipationType",
            "code": "PPRF",
            "display": "primary performer"
          } ],
          "text": "primary performer"
        } ],
        "period": {
          "start": "2019-01-28T05:37:16-08:00",
          "end": "2019-01-28T06:34:18-08:00"
        },
        "individual": {
          "reference": "Practitioner?identifier=http://hl7.org/fhir/sid/us-npi|9999963595",
          "display": "Dr. Jordon466 Bruen238"
        }
      } ],
      "period": {
        "start": "2019-01-28T05:37:16-08:00",
        "end": "2019-01-28T06:34:18-08:00"
      },
      "serviceProvider": {
        "reference": "Organization?identifier=https://github.com/synthetichealth/synthea|19f958ef-57cf-33c1-b068-14b32a980813",
        "display": "DRACUT FAMILY HEALTHCARE"
      }
    },
    "request": {
      "method": "POST",
      "url": "Encounter"
    }
  }, {
    "fullUrl": "urn:uuid:f9ab68c0-3458-b0f6-a69e-07880ca73235",
    "resource": {
      "resourceType": "Encounter",
      "id": "f9ab68c0-3458-b0f6-a69e-07880ca73235",
      "status": "finished",
      "class": {
        "system": "http://terminology.hl7.org/CodeSystem/v3-ActCode",
        "code": "AMB"
      },
      "type": [ {
        "coding": [ {
          "system": "http://snomed.info/sct",
          "code": "162673000",
          "display": "General examination of patient (procedure)"
        } ],
        "text": "General examination of patient (procedure)"
      } ],
      "subject": {
        "reference": "urn:uuid:8f2fa69d-5631-8623-dcf8-dabc5af99cf4",
        "display": "Mr. Seymour882 Lou594 Russel238"
      },
      "participant": [ {
        "type": [ {
          "coding": [ {
            "system": "http://terminology.hl7.org/CodeSystem/v3-ParticipationType",
            "code": "PPRF",
            "display": "primary performer"
          } ],
          "text": "primary performer"
        } ],
        "period": {
          "start": "2020-02-03T05:37:16-08:00",
          "end": "2020-02-03T06:32:04-08:00"
        },
        "individual": {
          "reference": "Practitioner?identifier=http://hl7.org/fhir/sid/us-npi|9999963595",
          "display": "Dr. Jordon466 Bruen238"
        }
      } ],
      "period": {
        "start": "2020-02-03T05:37:16-08:00",
        "end": "2020-02-03T06:32:04-08:00"
      },
      "serviceProvider": {
        "reference": "Organization?identifier=https://github.com/synthetichealth/synthea|19f958ef-57cf-33c1-b068-14b32a980813",
        "display": "DRACUT FAMILY HEALTHCARE"
      }
    },
    "request": {
      "method": "POST",
      "url": "Encounter"
    }
  }, {
    "fullUrl": "urn:uuid:bb026942-7b49-cba2-cc38-0c4fb531fe7a",
    "resource": {
      "resourceType": "Encounter",
      "id": "bb026942-7b49-cba2-cc38-0c4fb531fe7a",
      "status": "finished",
      "class": {
        "system": "http://terminology.hl7.org/CodeSystem/v3-ActCode",
        "code": "AMB"
      },
      "type": [ {
        "coding": [ {
          "system": "http://snomed.info/sct",
          "code": "162673000",
          "display": "General examination of patient (procedure)"
        } ],
        "text": "General examination of patient (procedure)"
      } ],
      "subject": {
        "reference": "urn:uuid:8f2fa69d-5631-8623-dcf8-dabc5af99cf4",
        "display": "Mr. Seymour882 Lou594 Russel238"
      },
      "participant": [ {
        "type": [ {
          "coding": [ {
            "system": "http://terminology.hl7.org/CodeSystem/v3-ParticipationType",
            "code": "PPRF",
            "display": "primary performer"
          } ],
          "text": "primary performer"
        } ],
        "period": {
          "start": "2021-02-08T05:37:16-08:00",
          "end": "2021-02-08T06:07:56-08:00"
        },
        "individual": {
          "reference": "Practitioner?identifier=http://hl7.org/fhir/sid/us-npi|9999963595",
          "display": "Dr. Jordon466 Bruen238"
        }
      } ],
      "period": {
        "start": "2021-02-08T05:37:16-08:00",
        "end": "2021-02-08T06:07:56-08:00"
      },
      "serviceProvider": {
        "reference": "Organization?identifier=https://github.com/synthetichealth/synthea|19f958ef-57cf-33c1-b068-14b32a980813",
        "display": "DRACUT FAMILY HEALTHCARE"
      }
    },
    "request": {
      "method": "POST",
      "url": "Encounter"
    }
  }, {
    "fullUrl": "urn:uuid:1326061d-31b9-01ae-3aad-1d6ec07b6914",
    "resource": {
      "resourceType": "Encounter",
      "id": "1326061d-31b9-01ae-3aad-1d6ec07b6914",
      "status": "finished",
      "class": {
        "system": "http://terminology.hl7.org/CodeSystem/v3-ActCode",
        "code": "AMB"
      },
      "type": [ {
        "coding": [ {
          "system": "http://snomed.info/sct",
          "code": "33879002",
          "display": "Administration of vaccine to produce active immunity (procedure)"
        } ],
        "text": "Administration of vaccine to produce active immunity (procedure)"
      } ],
      "subject": {
        "reference": "urn:uuid:8f2fa69d-5631-8623-dcf8-dabc5af99cf4",
        "display": "Mr. Seymour882 Lou594 Russel238"
      },
      "participant": [ {
        "type": [ {
          "coding": [ {
            "system": "http://terminology.hl7.org/CodeSystem/v3-ParticipationType",
            "code": "PPRF",
            "display": "primary performer"
          } ],
          "text": "primary performer"
        } ],
        "period": {
          "start": "2021-08-09T06:37:16-07:00",
          "end": "2021-08-09T06:52:16-07:00"
        },
        "individual": {
          "reference": "Practitioner?identifier=http://hl7.org/fhir/sid/us-npi|9999994491",
          "display": "Dr. Alysha630 Koch169"
        }
      } ],
      "period": {
        "start": "2021-08-09T06:37:16-07:00",
        "end": "2021-08-09T06:52:16-07:00"
      },
      "serviceProvider": {
        "reference": "Organization?identifier=https://github.com/synthetichealth/synthea|2836d9ac-c6a6-39d1-8f13-fdf0fc8928f4",
        "display": "TEWKSBURY HOSPITAL"
      }
    },
    "request": {
      "method": "POST",
      "url": "Encounter"
    }
  }, {
    "fullUrl": "urn:uuid:b02ae2fb-dd9c-6747-768c-f0d864b83be1",
    "resource": {
      "resourceType": "Encounter",
      "id": "b02ae2fb-dd9c-6747-768c-f0d864b83be1",
      "status": "finished",
      "class": {
        "system": "http://terminology.hl7.org/CodeSystem/v3-ActCode",
        "code": "AMB"
      },
      "type": [ {
        "coding": [ {
          "system": "http://snomed.info/sct",
          "code": "33879002",
          "display": "Administration of vaccine to produce active immunity (procedure)"
        } ],
        "text": "Administration of vaccine to produce active immunity (procedure)"
      } ],
      "subject": {
        "reference": "urn:uuid:8f2fa69d-5631-8623-dcf8-dabc5af99cf4",
        "display": "Mr. Seymour882 Lou594 Russel238"
      },
      "participant": [ {
        "type": [ {
          "coding": [ {
            "system": "http://terminology.hl7.org/CodeSystem/v3-ParticipationType",
            "code": "PPRF",
            "display": "primary performer"
          } ],
          "text": "primary performer"
        } ],
        "period": {
          "start": "2021-08-30T06:37:16-07:00",
          "end": "2021-08-30T06:52:16-07:00"
        },
        "individual": {
          "reference": "Practitioner?identifier=http://hl7.org/fhir/sid/us-npi|9999994491",
          "display": "Dr. Alysha630 Koch169"
        }
      } ],
      "period": {
        "start": "2021-08-30T06:37:16-07:00",
        "end": "2021-08-30T06:52:16-07:00"
      },
      "serviceProvider": {
        "reference": "Organization?identifier=https://github.com/synthetichealth/synthea|2836d9ac-c6a6-39d1-8f13-fdf0fc8928f4",
        "display": "TEWKSBURY HOSPITAL"
      }
    },
    "request": {
      "method": "POST",
      "url": "Encounter"
    }
  }, {
    "fullUrl": "urn:uuid:4264d056-9d45-6153-b080-2d38d83fc534",
    "resource": {
      "resourceType": "Encounter",
      "id": "4264d056-9d45-6153-b080-2d38d83fc534",
      "status": "finished",
      "class": {
        "system": "http://terminology.hl7.org/CodeSystem/v3-ActCode",
        "code": "AMB"
      },
      "type": [ {
        "coding": [ {
          "system": "http://snomed.info/sct",
          "code": "162673000",
          "display": "General examination of patient (procedure)"
        } ],
        "text": "General examination of patient (procedure)"
      } ],
      "subject": {
        "reference": "urn:uuid:8f2fa69d-5631-8623-dcf8-dabc5af99cf4",
        "display": "Mr. Seymour882 Lou594 Russel238"
      },
      "participant": [ {
        "type": [ {
          "coding": [ {
            "system": "http://terminology.hl7.org/CodeSystem/v3-ParticipationType",
            "code": "PPRF",
            "display": "primary performer"
          } ],
          "text": "primary performer"
        } ],
        "period": {
          "start": "2022-02-14T05:37:16-08:00",
          "end": "2022-02-14T06:17:53-08:00"
        },
        "individual": {
          "reference": "Practitioner?identifier=http://hl7.org/fhir/sid/us-npi|9999963595",
          "display": "Dr. Jordon466 Bruen238"
        }
      } ],
      "period": {
        "start": "2022-02-14T05:37:16-08:00",
        "end": "2022-02-14T06:17:53-08:00"
      },
      "serviceProvider": {
        "reference": "Organization?identifier=https://github.com/synthetichealth/synthea|19f958ef-57cf-33c1-b068-14b32a980813",
        "display": "DRACUT FAMILY HEALTHCARE"
      }
    },
    "request": {
      "method": "POST",
      "url": "Encounter"
    }
  }, {
    "fullUrl": "urn:uuid:f34119e8-5de8-3a74-d46b-e2804c928575",
    "resource": {
      "resourceType": "Encounter",
      "id": "f34119e8-5de8-3a74-d46b-e2804c928575",
      "status": "finished",
      "class": {
        "system": "http://terminology.hl7.org/CodeSystem/v3-ActCode",
        "code": "AMB"
      },
      "type": [ {
        "coding": [ {
          "system": "http://snomed.info/sct",
          "code": "702927004",
          "display": "Urgent care clinic (environment)"
        } ],
        "text": "Urgent care clinic (environment)"
      } ],
      "subject": {
        "reference": "urn:uuid:8f2fa69d-5631-8623-dcf8-dabc5af99cf4",
        "display": "Mr. Seymour882 Lou594 Russel238"
      },
      "participant": [ {
        "type": [ {
          "coding": [ {
            "system": "http://terminology.hl7.org/CodeSystem/v3-ParticipationType",
            "code": "PPRF",
            "display": "primary performer"
          } ],
          "text": "primary performer"
        } ],
        "period": {
          "start": "2022-02-21T05:37:16-08:00",
          "end": "2022-02-21T05:52:16-08:00"
        },
        "individual": {
          "reference": "Practitioner?identifier=http://hl7.org/fhir/sid/us-npi|9999938498",
          "display": "Dr. Rema399 McDermott739"
        }
      } ],
      "period": {
        "start": "2022-02-21T05:37:16-08:00",
        "end": "2022-02-21T05:52:16-08:00"
      },
      "serviceProvider": {
        "reference": "Organization?identifier=https://github.com/synthetichealth/synthea|c05d73d0-b348-32ce-9fe5-13a720950f37",
        "display": "URGENT HELP CHELMSFORD PC"
      }
    },
    "request": {
      "method": "POST",
      "url": "Encounter"
    }
  }, {
    "fullUrl": "urn:uuid:29a23961-eec3-046f-59b8-b68fc5a341f7",
    "resource": {
      "resourceType": "Encounter",
      "id": "29a23961-eec3-046f-59b8-b68fc5a341f7",
      "status": "finished",
      "class": {
        "system": "http://terminology.hl7.org/CodeSystem/v3-ActCode",
        "code": "AMB"
      },
      "type": [ {
        "coding": [ {
          "system": "http://snomed.info/sct",
          "code": "702927004",
          "display": "Urgent care clinic (environment)"
        } ],
        "text": "Urgent care clinic (environment)"
      } ],
      "subject": {
        "reference": "urn:uuid:8f2fa69d-5631-8623-dcf8-dabc5af99cf4",
        "display": "Mr. Seymour882 Lou594 Russel238"
      },
      "participant": [ {
        "type": [ {
          "coding": [ {
            "system": "http://terminology.hl7.org/CodeSystem/v3-ParticipationType",
            "code": "PPRF",
            "display": "primary performer"
          } ],
          "text": "primary performer"
        } ],
        "period": {
          "start": "2022-02-28T05:37:16-08:00",
          "end": "2022-02-28T06:22:19-08:00"
        },
        "individual": {
          "reference": "Practitioner?identifier=http://hl7.org/fhir/sid/us-npi|9999938498",
          "display": "Dr. Rema399 McDermott739"
        }
      } ],
      "period": {
        "start": "2022-02-28T05:37:16-08:00",
        "end": "2022-02-28T06:22:19-08:00"
      },
      "serviceProvider": {
        "reference": "Organization?identifier=https://github.com/synthetichealth/synthea|c05d73d0-b348-32ce-9fe5-13a720950f37",
        "display": "URGENT HELP CHELMSFORD PC"
      }
    },
    "request": {
      "method": "POST",
      "url": "Encounter"
    }
  }, {
    "fullUrl": "urn:uuid:ee3814cd-ac9c-5d03-37fb-46491e75afaa",
    "resource": {
      "resourceType": "Encounter",
      "id": "ee3814cd-ac9c-5d03-37fb-46491e75afaa",
      "status": "finished",
      "class": {
        "system": "http://terminology.hl7.org/CodeSystem/v3-ActCode",
        "code": "AMB"
      },
      "type": [ {
        "coding": [ {
          "system": "http://snomed.info/sct",
          "code": "185349003",
          "display": "Encounter for check up (procedure)"
        } ],
        "text": "Encounter for check up (procedure)"
      } ],
      "subject": {
        "reference": "urn:uuid:8f2fa69d-5631-8623-dcf8-dabc5af99cf4",
        "display": "Mr. Seymour882 Lou594 Russel238"
      },
      "participant": [ {
        "type": [ {
          "coding": [ {
            "system": "http://terminology.hl7.org/CodeSystem/v3-ParticipationType",
            "code": "PPRF",
            "display": "primary performer"
          } ],
          "text": "primary performer"
        } ],
        "period": {
          "start": "2022-03-07T05:37:16-08:00",
          "end": "2022-03-07T05:52:16-08:00"
        },
        "individual": {
          "reference": "Practitioner?identifier=http://hl7.org/fhir/sid/us-npi|9999994491",
          "display": "Dr. Alysha630 Koch169"
        }
      } ],
      "period": {
        "start": "2022-03-07T05:37:16-08:00",
        "end": "2022-03-07T05:52:16-08:00"
      },
      "serviceProvider": {
        "reference": "Organization?identifier=https://github.com/synthetichealth/synthea|2836d9ac-c6a6-39d1-8f13-fdf0fc8928f4",
        "display": "TEWKSBURY HOSPITAL"
      }
    },
    "request": {
      "method": "POST",
      "url": "Encounter"
    }
  }, {
    "fullUrl": "urn:uuid:121c9252-74c7-4c8d-2c9b-7f9e1b7afe48",
    "resource": {
      "resourceType": "Encounter",
      "id": "121c9252-74c7-4c8d-2c9b-7f9e1b7afe48",
      "status": "finished",
      "class": {
        "system": "http://terminology.hl7.org/CodeSystem/v3-ActCode",
        "code": "AMB"
      },
      "type": [ {
        "coding": [ {
          "system": "http://snomed.info/sct",
          "code": "185345009",
          "display": "Encounter for symptom"
        } ],
        "text": "Encounter for symptom"
      } ],
      "subject": {
        "reference": "urn:uuid:8f2fa69d-5631-8623-dcf8-dabc5af99cf4",
        "display": "Mr. Seymour882 Lou594 Russel238"
      },
      "participant": [ {
        "type": [ {
          "coding": [ {
            "system": "http://terminology.hl7.org/CodeSystem/v3-ParticipationType",
            "code": "PPRF",
            "display": "primary performer"
          } ],
          "text": "primary performer"
        } ],
        "period": {
          "start": "2022-03-14T06:37:16-07:00",
          "end": "2022-03-14T06:52:16-07:00"
        },
        "individual": {
          "reference": "Practitioner?identifier=http://hl7.org/fhir/sid/us-npi|9999994491",
          "display": "Dr. Alysha630 Koch169"
        }
      } ],
      "period": {
        "start": "2022-03-14T06:37:16-07:00",
        "end": "2022-03-14T06:52:16-07:00"
      },
      "reasonCode": [ {
        "coding": [ {
          "system": "http://snomed.info/sct",
          "code": "444814009",
          "display": "Viral sinusitis (disorder)"
        } ]
      } ],
      "serviceProvider": {
        "reference": "Organization?identifier=https://github.com/synthetichealth/synthea|2836d9ac-c6a6-39d1-8f13-fdf0fc8928f4",
        "display": "TEWKSBURY HOSPITAL"
      }
    },
    "request": {
      "method": "POST",
      "url": "Encounter"
    }
  }, {
    "fullUrl": "urn:uuid:6bcf43df-01ba-1dab-8948-3d5a3854342b",
    "resource": {
      "resourceType": "Encounter",
      "id": "6bcf43df-01ba-1dab-8948-3d5a3854342b",
      "status": "finished",
      "class": {
        "system": "http://terminology.hl7.org/CodeSystem/v3-ActCode",
        "code": "AMB"
      },
      "type": [ {
        "coding": [ {
          "system": "http://snomed.info/sct",
          "code": "702927004",
          "display": "Urgent care clinic (environment)"
        } ],
        "text": "Urgent care clinic (environment)"
      } ],
      "subject": {
        "reference": "urn:uuid:8f2fa69d-5631-8623-dcf8-dabc5af99cf4",
        "display": "Mr. Seymour882 Lou594 Russel238"
      },
      "participant": [ {
        "type": [ {
          "coding": [ {
            "system": "http://terminology.hl7.org/CodeSystem/v3-ParticipationType",
            "code": "PPRF",
            "display": "primary performer"
          } ],
          "text": "primary performer"
        } ],
        "period": {
          "start": "2022-03-21T06:37:16-07:00",
          "end": "2022-03-21T07:18:50-07:00"
        },
        "individual": {
          "reference": "Practitioner?identifier=http://hl7.org/fhir/sid/us-npi|9999938498",
          "display": "Dr. Rema399 McDermott739"
        }
      } ],
      "period": {
        "start": "2022-03-21T06:37:16-07:00",
        "end": "2022-03-21T07:18:50-07:00"
      },
      "serviceProvider": {
        "reference": "Organization?identifier=https://github.com/synthetichealth/synthea|c05d73d0-b348-32ce-9fe5-13a720950f37",
        "display": "URGENT HELP CHELMSFORD PC"
      }
    },
    "request": {
      "method": "POST",
      "url": "Encounter"
    }
  }, {
    "fullUrl": "urn:uuid:45773439-8d29-6ecb-b794-dfe844f60311",
    "resource": {
      "resourceType": "Encounter",
      "id": "45773439-8d29-6ecb-b794-dfe844f60311",
      "status": "finished",
      "class": {
        "system": "http://terminology.hl7.org/CodeSystem/v3-ActCode",
        "code": "AMB"
      },
      "type": [ {
        "coding": [ {
          "system": "http://snomed.info/sct",
          "code": "702927004",
          "display": "Urgent care clinic (environment)"
        } ],
        "text": "Urgent care clinic (environment)"
      } ],
      "subject": {
        "reference": "urn:uuid:8f2fa69d-5631-8623-dcf8-dabc5af99cf4",
        "display": "Mr. Seymour882 Lou594 Russel238"
      },
      "participant": [ {
        "type": [ {
          "coding": [ {
            "system": "http://terminology.hl7.org/CodeSystem/v3-ParticipationType",
            "code": "PPRF",
            "display": "primary performer"
          } ],
          "text": "primary performer"
        } ],
        "period": {
          "start": "2022-03-28T06:37:16-07:00",
          "end": "2022-03-28T06:52:16-07:00"
        },
        "individual": {
          "reference": "Practitioner?identifier=http://hl7.org/fhir/sid/us-npi|9999938498",
          "display": "Dr. Rema399 McDermott739"
        }
      } ],
      "period": {
        "start": "2022-03-28T06:37:16-07:00",
        "end": "2022-03-28T06:52:16-07:00"
      },
      "serviceProvider": {
        "reference": "Organization?identifier=https://github.com/synthetichealth/synthea|c05d73d0-b348-32ce-9fe5-13a720950f37",
        "display": "URGENT HELP CHELMSFORD PC"
      }
    },
    "request": {
      "method": "POST",
      "url": "Encounter"
    }
  }, {
    "fullUrl": "urn:uuid:51d969ee-778f-f088-a9ef-37782d90003a",
    "resource": {
      "resourceType": "Encounter",
      "id": "51d969ee-778f-f088-a9ef-37782d90003a",
      "status": "finished",
      "class": {
        "system": "http://terminology.hl7.org/CodeSystem/v3-ActCode",
        "code": "AMB"
      },
      "type": [ {
        "coding": [ {
          "system": "http://snomed.info/sct",
          "code": "185349003",
          "display": "Encounter for check up (procedure)"
        } ],
        "text": "Encounter for check up (procedure)"
      } ],
      "subject": {
        "reference": "urn:uuid:8f2fa69d-5631-8623-dcf8-dabc5af99cf4",
        "display": "Mr. Seymour882 Lou594 Russel238"
      },
      "participant": [ {
        "type": [ {
          "coding": [ {
            "system": "http://terminology.hl7.org/CodeSystem/v3-ParticipationType",
            "code": "PPRF",
            "display": "primary performer"
          } ],
          "text": "primary performer"
        } ],
        "period": {
          "start": "2022-06-20T06:37:16-07:00",
          "end": "2022-06-20T07:30:40-07:00"
        },
        "individual": {
          "reference": "Practitioner?identifier=http://hl7.org/fhir/sid/us-npi|9999994491",
          "display": "Dr. Alysha630 Koch169"
        }
      } ],
      "period": {
        "start": "2022-06-20T06:37:16-07:00",
        "end": "2022-06-20T07:30:40-07:00"
      },
      "serviceProvider": {
        "reference": "Organization?identifier=https://github.com/synthetichealth/synthea|2836d9ac-c6a6-39d1-8f13-fdf0fc8928f4",
        "display": "TEWKSBURY HOSPITAL"
      }
    },
    "request": {
      "method": "POST",
      "url": "Encounter"
    }
  }, {
    "fullUrl": "urn:uuid:3961bfd3-34ac-fddf-db75-6b2ef9a3164c",
    "resource": {
      "resourceType": "Encounter",
      "id": "3961bfd3-34ac-fddf-db75-6b2ef9a3164c",
      "status": "finished",
      "class": {
        "system": "http://terminology.hl7.org/CodeSystem/v3-ActCode",
        "code": "AMB"
      },
      "type": [ {
        "coding": [ {
          "system": "http://snomed.info/sct",
          "code": "185349003",
          "display": "Encounter for check up (procedure)"
        } ],
        "text": "Encounter for check up (procedure)"
      } ],
      "subject": {
        "reference": "urn:uuid:8f2fa69d-5631-8623-dcf8-dabc5af99cf4",
        "display": "Mr. Seymour882 Lou594 Russel238"
      },
      "participant": [ {
        "type": [ {
          "coding": [ {
            "system": "http://terminology.hl7.org/CodeSystem/v3-ParticipationType",
            "code": "PPRF",
            "display": "primary performer"
          } ],
          "text": "primary performer"
        } ],
        "period": {
          "start": "2022-07-18T06:37:16-07:00",
          "end": "2022-07-18T07:35:44-07:00"
        },
        "individual": {
          "reference": "Practitioner?identifier=http://hl7.org/fhir/sid/us-npi|9999994491",
          "display": "Dr. Alysha630 Koch169"
        }
      } ],
      "period": {
        "start": "2022-07-18T06:37:16-07:00",
        "end": "2022-07-18T07:35:44-07:00"
      },
      "serviceProvider": {
        "reference": "Organization?identifier=https://github.com/synthetichealth/synthea|2836d9ac-c6a6-39d1-8f13-fdf0fc8928f4",
        "display": "TEWKSBURY HOSPITAL"
      }
    },
    "request": {
      "method": "POST",
      "url": "Encounter"
    }
  }, {
    "fullUrl": "urn:uuid:ccad41cc-62cc-9753-a1d8-e7e019bc189b",
    "resource": {
      "resourceType": "Encounter",
      "id": "ccad41cc-62cc-9753-a1d8-e7e019bc189b",
      "status": "finished",
      "class": {
        "system": "http://terminology.hl7.org/CodeSystem/v3-ActCode",
        "code": "AMB"
      },
      "type": [ {
        "coding": [ {
          "system": "http://snomed.info/sct",
          "code": "162673000",
          "display": "General examination of patient (procedure)"
        } ],
        "text": "General examination of patient (procedure)"
      } ],
      "subject": {
        "reference": "urn:uuid:8f2fa69d-5631-8623-dcf8-dabc5af99cf4",
        "display": "Mr. Seymour882 Lou594 Russel238"
      },
      "participant": [ {
        "type": [ {
          "coding": [ {
            "system": "http://terminology.hl7.org/CodeSystem/v3-ParticipationType",
            "code": "PPRF",
            "display": "primary performer"
          } ],
          "text": "primary performer"
        } ],
        "period": {
          "start": "2023-02-20T05:37:16-08:00",
          "end": "2023-02-20T06:26:43-08:00"
        },
        "individual": {
          "reference": "Practitioner?identifier=http://hl7.org/fhir/sid/us-npi|9999963595",
          "display": "Dr. Jordon466 Bruen238"
        }
      } ],
      "period": {
        "start": "2023-02-20T05:37:16-08:00",
        "end": "2023-02-20T06:26:43-08:00"
      },
      "serviceProvider": {
        "reference": "Organization?identifier=https://github.com/synthetichealth/synthea|19f958ef-57cf-33c1-b068-14b32a980813",
        "display": "DRACUT FAMILY HEALTHCARE"
      }
    },
    "request": {
      "method": "POST",
      "url": "Encounter"
    }
  }, {
    "fullUrl": "urn:uuid:2a04c8c2-9c92-3193-f431-1a8f64bbf3e0",
    "resource": {
      "resourceType": "Encounter",
      "id": "2a04c8c2-9c92-3193-f431-1a8f64bbf3e0",
      "status": "finished",
      "class": {
        "system": "http://terminology.hl7.org/CodeSystem/v3-ActCode",
        "code": "AMB"
      },
      "type": [ {
        "coding": [ {
          "system": "http://snomed.info/sct",
          "code": "185349003",
          "display": "Encounter for check up (procedure)"
        } ],
        "text": "Encounter for check up (procedure)"
      } ],
      "subject": {
        "reference": "urn:uuid:8f2fa69d-5631-8623-dcf8-dabc5af99cf4",
        "display": "Mr. Seymour882 Lou594 Russel238"
      },
      "participant": [ {
        "type": [ {
          "coding": [ {
            "system": "http://terminology.hl7.org/CodeSystem/v3-ParticipationType",
            "code": "PPRF",
            "display": "primary performer"
          } ],
          "text": "primary performer"
        } ],
        "period": {
          "start": "2023-04-17T06:37:16-07:00",
          "end": "2023-04-17T07:32:28-07:00"
        },
        "individual": {
          "reference": "Practitioner?identifier=http://hl7.org/fhir/sid/us-npi|9999994491",
          "display": "Dr. Alysha630 Koch169"
        }
      } ],
      "period": {
        "start": "2023-04-17T06:37:16-07:00",
        "end": "2023-04-17T07:32:28-07:00"
      },
      "serviceProvider": {
        "reference": "Organization?identifier=https://github.com/synthetichealth/synthea|2836d9ac-c6a6-39d1-8f13-fdf0fc8928f4",
        "display": "TEWKSBURY HOSPITAL"
      }
    },
    "request": {
      "method": "POST",
      "url": "Encounter"
    }
  }, {
    "fullUrl": "urn:uuid:a8077151-aa85-8d7a-ddda-54dac86fee47",
    "resource": {
      "resourceType": "Encounter",
      "id": "a8077151-aa85-8d7a-ddda-54dac86fee47",
      "status": "finished",
      "class": {
        "system": "http://terminology.hl7.org/CodeSystem/v3-ActCode",
        "code": "AMB"
      },
      "type": [ {
        "coding": [ {
          "system": "http://snomed.info/sct",
          "code": "702927004",
          "display": "Urgent care clinic (environment)"
        } ],
        "text": "Urgent care clinic (environment)"
      } ],
      "subject": {
        "reference": "urn:uuid:8f2fa69d-5631-8623-dcf8-dabc5af99cf4",
        "display": "Mr. Seymour882 Lou594 Russel238"
      },
      "participant": [ {
        "type": [ {
          "coding": [ {
            "system": "http://terminology.hl7.org/CodeSystem/v3-ParticipationType",
            "code": "PPRF",
            "display": "primary performer"
          } ],
          "text": "primary performer"
        } ],
        "period": {
          "start": "2023-10-16T06:37:16-07:00",
          "end": "2023-10-16T07:28:59-07:00"
        },
        "individual": {
          "reference": "Practitioner?identifier=http://hl7.org/fhir/sid/us-npi|9999938498",
          "display": "Dr. Rema399 McDermott739"
        }
      } ],
      "period": {
        "start": "2023-10-16T06:37:16-07:00",
        "end": "2023-10-16T07:28:59-07:00"
      },
      "serviceProvider": {
        "reference": "Organization?identifier=https://github.com/synthetichealth/synthea|c05d73d0-b348-32ce-9fe5-13a720950f37",
        "display": "URGENT HELP CHELMSFORD PC"
      }
    },
    "request": {
      "method": "POST",
      "url": "Encounter"
    }
  }, {
    "fullUrl": "urn:uuid:16af8eed-74f1-84b1-cd9f-1204aae23fe9",
    "resource": {
      "resourceType": "Encounter",
      "id": "16af8eed-74f1-84b1-cd9f-1204aae23fe9",
      "status": "finished",
      "class": {
        "system": "http://terminology.hl7.org/CodeSystem/v3-ActCode",
        "code": "AMB"
      },
      "type": [ {
        "coding": [ {
          "system": "http://snomed.info/sct",
          "code": "702927004",
          "display": "Urgent care clinic (environment)"
        } ],
        "text": "Urgent care clinic (environment)"
      } ],
      "subject": {
        "reference": "urn:uuid:8f2fa69d-5631-8623-dcf8-dabc5af99cf4",
        "display": "Mr. Seymour882 Lou594 Russel238"
      },
      "participant": [ {
        "type": [ {
          "coding": [ {
            "system": "http://terminology.hl7.org/CodeSystem/v3-ParticipationType",
            "code": "PPRF",
            "display": "primary performer"
          } ],
          "text": "primary performer"
        } ],
        "period": {
          "start": "2023-12-11T05:37:16-08:00",
          "end": "2023-12-11T06:13:07-08:00"
        },
        "individual": {
          "reference": "Practitioner?identifier=http://hl7.org/fhir/sid/us-npi|9999938498",
          "display": "Dr. Rema399 McDermott739"
        }
      } ],
      "period": {
        "start": "2023-12-11T05:37:16-08:00",
        "end": "2023-12-11T06:13:07-08:00"
      },
      "serviceProvider": {
        "reference": "Organization?identifier=https://github.com/synthetichealth/synthea|c05d73d0-b348-32ce-9fe5-13a720950f37",
        "display": "URGENT HELP CHELMSFORD PC"
      }
    },
    "request": {
      "method": "POST",
      "url": "Encounter"
    }
  }, {
    "fullUrl": "urn:uuid:20f79be5-c7a3-27bd-20f9-0540b601849d",
    "resource": {
      "resourceType": "Encounter",
      "id": "20f79be5-c7a3-27bd-20f9-0540b601849d",
      "status": "finished",
      "class": {
        "system": "http://terminology.hl7.org/CodeSystem/v3-ActCode",
        "code": "AMB"
      },
      "type": [ {
        "coding": [ {
          "system": "http://snomed.info/sct",
          "code": "702927004",
          "display": "Urgent care clinic (environment)"
        } ],
        "text": "Urgent care clinic (environment)"
      } ],
      "subject": {
        "reference": "urn:uuid:8f2fa69d-5631-8623-dcf8-dabc5af99cf4",
        "display": "Mr. Seymour882 Lou594 Russel238"
      },
      "participant": [ {
        "type": [ {
          "coding": [ {
            "system": "http://terminology.hl7.org/CodeSystem/v3-ParticipationType",
            "code": "PPRF",
            "display": "primary performer"
          } ],
          "text": "primary performer"
        } ],
        "period": {
          "start": "2024-02-12T05:37:16-08:00",
          "end": "2024-02-12T06:23:16-08:00"
        },
        "individual": {
          "reference": "Practitioner?identifier=http://hl7.org/fhir/sid/us-npi|9999938498",
          "display": "Dr. Rema399 McDermott739"
        }
      } ],
      "period": {
        "start": "2024-02-12T05:37:16-08:00",
        "end": "2024-02-12T06:23:16-08:00"
      },
      "serviceProvider": {
        "reference": "Organization?identifier=https://github.com/synthetichealth/synthea|c05d73d0-b348-32ce-9fe5-13a720950f37",
        "display": "URGENT HELP CHELMSFORD PC"
      }
    },
    "request": {
      "method": "POST",
      "url": "Encounter"
    }
  }, {
    "fullUrl": "urn:uuid:4bccb6b3-8ece-0904-7a66-b9b0441e04cd",
    "resource": {
      "resourceType": "Encounter",
      "id": "4bccb6b3-8ece-0904-7a66-b9b0441e04cd",
      "status": "finished",
      "class": {
        "system": "http://terminology.hl7.org/CodeSystem/v3-ActCode",
        "code": "AMB"
      },
      "type": [ {
        "coding": [ {
          "system": "http://snomed.info/sct",
          "code": "162673000",
          "display": "General examination of patient (procedure)"
        } ],
        "text": "General examination of patient (procedure)"
      } ],
      "subject": {
        "reference": "urn:uuid:8f2fa69d-5631-8623-dcf8-dabc5af99cf4",
        "display": "Mr. Seymour882 Lou594 Russel238"
      },
      "participant": [ {
        "type": [ {
          "coding": [ {
            "system": "http://terminology.hl7.org/CodeSystem/v3-ParticipationType",
            "code": "PPRF",
            "display": "primary performer"
          } ],
          "text": "primary performer"
        } ],
        "period": {
          "start": "2024-02-26T05:37:16-08:00",
          "end": "2024-02-26T06:13:12-08:00"
        },
        "individual": {
          "reference": "Practitioner?identifier=http://hl7.org/fhir/sid/us-npi|9999963595",
          "display": "Dr. Jordon466 Bruen238"
        }
      } ],
      "period": {
        "start": "2024-02-26T05:37:16-08:00",
        "end": "2024-02-26T06:13:12-08:00"
      },
      "serviceProvider": {
        "reference": "Organization?identifier=https://github.com/synthetichealth/synthea|19f958ef-57cf-33c1-b068-14b32a980813",
        "display": "DRACUT FAMILY HEALTHCARE"
      }
    },
    "request": {
      "method": "POST",
      "url": "Encounter"
    }
  }, {
    "fullUrl": "urn:uuid:75f3adff-2dd8-e257-d853-7b80ab6f57f4",
    "resource": {
      "resourceType": "Encounter",
      "id": "75f3adff-2dd8-e257-d853-7b80ab6f57f4",
      "status": "finished",
      "class": {
        "system": "http://terminology.hl7.org/CodeSystem/v3-ActCode",
        "code": "AMB"
      },
      "type": [ {
        "coding": [ {
          "system": "http://snomed.info/sct",
          "code": "185349003",
          "display": "Encounter for check up (procedure)"
        } ],
        "text": "Encounter for check up (procedure)"
      } ],
      "subject": {
        "reference": "urn:uuid:8f2fa69d-5631-8623-dcf8-dabc5af99cf4",
        "display": "Mr. Seymour882 Lou594 Russel238"
      },
      "participant": [ {
        "type": [ {
          "coding": [ {
            "system": "http://terminology.hl7.org/CodeSystem/v3-ParticipationType",
            "code": "PPRF",
            "display": "primary performer"
          } ],
          "text": "primary performer"
        } ],
        "period": {
          "start": "2024-03-11T06:37:16-07:00",
          "end": "2024-03-11T07:22:51-07:00"
        },
        "individual": {
          "reference": "Practitioner?identifier=http://hl7.org/fhir/sid/us-npi|9999994491",
          "display": "Dr. Alysha630 Koch169"
        }
      } ],
      "period": {
        "start": "2024-03-11T06:37:16-07:00",
        "end": "2024-03-11T07:22:51-07:00"
      },
      "serviceProvider": {
        "reference": "Organization?identifier=https://github.com/synthetichealth/synthea|2836d9ac-c6a6-39d1-8f13-fdf0fc8928f4",
        "display": "TEWKSBURY HOSPITAL"
      }
    },
    "request": {
      "method": "POST",
      "url": "Encounter"
    }
  } ]
}
